{
    "type": "RT",
    "points": [
        {
            "type": "Next",
            "name": "003SPBECICE",
            "altitude": 433.0,
            "lat": 49.38305000000024,
            "lng": 14.554166666666587,
            "radius": 7500
        },
        {
            "type": "Symmetric",
            "name": "212IMUNTEREN",
            "altitude": 490.0,
            "lat": 49.87499999999989,
            "lng": 12.326383333333313,
            "radius": 500
        },
        {
            "type": "Symmetric",
            "name": "095CUPRINA",
            "altitude": 864.0,
            "lat": 49.95194999999992,
            "lng": 12.485550000000115,
            "radius": 500
        },
        {
            "type": "Cylinder",
            "name": "001SPTABOR",
            "altitude": 428.0,
            "lat": 49.39416666666691,
            "lng": 14.702783333333127,
            "radius": 5000
        }
    ]
}